PyMusicOrganizer/__init__.py
PyMusicOrganizer/__main__.py
PyMusicOrganizer/main.py
PyMusicOrganizer/utils.py
PyMusicOrganizer-0.0.4.dist-info/LICENSE
PyMusicOrganizer-0.0.4.dist-info/METADATA
PyMusicOrganizer-0.0.4.dist-info/WHEEL
PyMusicOrganizer-0.0.4.dist-info/top_level.txt
PyMusicOrganizer-0.0.4.dist-info/RECORD
