Metadata-Version: 2.1
Name: PyMusicOrganizer
Version: 0.0.4
Summary: CLI tool to keep your music organized.
Home-page: https://github.com/g-battaglia/pymusicorganizer
Author: Giacomo Battaglia
Author-email: battaglia.giacomo@yahoo.it
Classifier: Development Status :: 1 - Planning
Classifier: Topic :: Multimedia :: Sound/Audio
Classifier: Typing :: Typed
Requires-Python: >=3.8
License-File: LICENSE
Requires-Dist: mutagen
Requires-Dist: pathlib
Requires-Dist: typer
Requires-Dist: rich
